stata_kernel/__init__.py
stata_kernel/__main__.py
stata_kernel/ado/_StataKernelCompletions.ado
stata_kernel/ado/_StataKernelHead.ado
stata_kernel/ado/_StataKernelLog.ado
stata_kernel/ado/_StataKernelResetRC.ado
stata_kernel/ado/_StataKernelTail.ado
stata_kernel/code_manager.py
stata_kernel/codemirror/stata.js
stata_kernel/completions.py
stata_kernel/config.py
stata_kernel/css/_StataKernelHelpDefault.css
stata_kernel/docs/css/pandoc.css
stata_kernel/docs/index.html
stata_kernel/docs/index.txt
stata_kernel/docs/logo-64x64.png
stata_kernel/docs/make.sh
stata_kernel/docs/make_href
stata_kernel/docs/using_stata_kernel/magics.html
stata_kernel/docs/using_stata_kernel/magics.txt
stata_kernel/install.py
stata_kernel/kernel.py
stata_kernel/pygments/_mata_builtins.py
stata_kernel/pygments/stata.py
stata_kernel/stata_lexer.py
stata_kernel/stata_magics.py
stata_kernel/stata_session.py
stata_kernel/utils.py
stata_kernel-1.14.2.dist-info/LICENSE
stata_kernel-1.14.2.dist-info/METADATA
stata_kernel-1.14.2.dist-info/WHEEL
stata_kernel-1.14.2.dist-info/RECORD
